<?xml version="1.0" encoding="UTF-8"?>
<!--
  ~ Alice's simple quiz maker - fun quizzes for curious minds
  ~ Copyright (C) 2026 Saidone
  ~
  ~ This program is free software: you can redistribute it and/or modify
  ~ it under the terms of the GNU General Public License as published by
  ~ the Free Software Foundation, either version 3 of the License, or
  ~ (at your option) any later version.
  ~
  ~  This program is distributed in the hope that it will be useful,
  ~  but WITHOUT ANY WARRANTY; without even the implied warranty of
  ~  MERCHANTABILITY or FITNESS FOR A PARTICULAR PURPOSE.  See the
  ~  GNU General Public License for more details.
  ~
  ~  You should have received a copy of the GNU General Public License
  ~  along with this program.  If not, see <http://www.gnu.org/licenses/>.
  -->

<databaseChangeLog
        xmlns="http://www.liquibase.org/xml/ns/dbchangelog"
        xmlns:xsi="http://www.w3.org/2001/XMLSchema-instance"
        xsi:schemaLocation="http://www.liquibase.org/xml/ns/dbchangelog
        http://www.liquibase.org/xml/ns/dbchangelog/dbchangelog-4.20.xsd">

    <changeSet id="002-quiz-archive-flag-h2-postgres" author="quizmaker" dbms="h2,postgresql">
        <preConditions onFail="MARK_RAN" onError="MARK_RAN">
            <not>
                <columnExists tableName="quizzes" columnName="archived"/>
            </not>
        </preConditions>

        <addColumn tableName="quizzes">
            <column name="archived" type="BOOLEAN" defaultValueBoolean="false">
                <constraints nullable="false"/>
            </column>
        </addColumn>

        <rollback>
            <dropColumn tableName="quizzes" columnName="archived"/>
        </rollback>
    </changeSet>

    <changeSet id="002-quiz-archive-flag-sqlite" author="quizmaker" dbms="sqlite">
        <preConditions onFail="MARK_RAN" onError="MARK_RAN">
            <not>
                <columnExists tableName="quizzes" columnName="archived"/>
            </not>
        </preConditions>

        <addColumn tableName="quizzes">
            <column name="archived" type="INTEGER" defaultValueNumeric="0">
                <constraints nullable="false"/>
            </column>
        </addColumn>

        <rollback>
            <dropColumn tableName="quizzes" columnName="archived"/>
        </rollback>
    </changeSet>

</databaseChangeLog>
